youtube_summariser/__init__.py
youtube_summariser/__main__.py
youtube_summariser/cli.py
youtube_summariser/config.yaml
youtube_summariser/llm_client.py
youtube_summariser/youtube_helper.py
youtube_summariser-0.3.2.dist-info/METADATA
youtube_summariser-0.3.2.dist-info/WHEEL
youtube_summariser-0.3.2.dist-info/entry_points.txt
youtube_summariser-0.3.2.dist-info/licenses/LICENSE
youtube_summariser-0.3.2.dist-info/RECORD
