Metadata-Version: 2.4
Name: youtube-summariser
Version: 0.3.2
Summary: Summarize YouTube videos using AI (OpenAI or Anthropic)
Project-URL: Homepage, https://github.com/weijianzhg/youtube-summariser
Project-URL: Repository, https://github.com/weijianzhg/youtube-summariser
Project-URL: Issues, https://github.com/weijianzhg/youtube-summariser/issues
Author: Weijian Zhang
License-Expression: MIT
License-File: LICENSE
Keywords: ai,anthropic,claude,cli,gpt,openai,summarizer,transcript,youtube
Classifier: Development Status :: 4 - Beta
Classifier: Environment :: Console
Classifier: Intended Audience :: Developers
Classifier: Intended Audience :: End Users/Desktop
Classifier: License :: OSI Approved :: MIT License
Classifier: Operating System :: OS Independent
Classifier: Programming Language :: Python :: 3
Classifier: Programming Language :: Python :: 3.10
Classifier: Programming Language :: Python :: 3.11
Classifier: Programming Language :: Python :: 3.12
Classifier: Programming Language :: Python :: 3.13
Classifier: Topic :: Multimedia :: Video
Classifier: Topic :: Text Processing :: General
Classifier: Topic :: Utilities
Requires-Python: >=3.10
Requires-Dist: anthropic>=0.40.0
Requires-Dist: openai>=1.60.0
Requires-Dist: python-dotenv>=1.0.0
Requires-Dist: pyyaml>=6.0
Requires-Dist: youtube-transcript-api>=1.0.0
Provides-Extra: dev
Requires-Dist: pytest-cov>=4.0.0; extra == 'dev'
Requires-Dist: pytest>=7.0.0; extra == 'dev'
Requires-Dist: ruff>=0.1.0; extra == 'dev'
